gr311/__init__.py
gr311/functions.py
gr311/geogr.py
grdata-0.0.6.dist-info/LICENSE
grdata-0.0.6.dist-info/METADATA
grdata-0.0.6.dist-info/WHEEL
grdata-0.0.6.dist-info/top_level.txt
grdata-0.0.6.dist-info/RECORD
