Metadata-Version: 2.1
Name: grdata
Version: 0.0.6
Summary: Package to process data using the City of Grand Rapids systems
Home-page: https://github.com/GRInnovation/grdata
Author: Zac Thiel
Author-email: digitalservices@grcity.us
License: UNKNOWN
Platform: UNKNOWN
Classifier: Programming Language :: Python :: 3
Classifier: License :: OSI Approved :: MIT License
Classifier: Operating System :: OS Independent
Requires-Python: >=3.7
